[{"id":1585924169625,"name":"Infinite Apostles And Twelve War Girls","alternative_name":"無限使徒和十二個戰爭女孩","url":"/infinite-apostles-and-twelve-war-girls","photo":"/uploads/posters/1585838925.jpg","status":"Ongoing","type":"Chinese","total_views":"0","date_crawled":"2020/04/03","authors":[{"name":"Lukezrc","url":"/people/lukezrc"}],"categories":[{"name":"Action","url":"/category/action"},{"name":"Adventure","url":"/category/adventure"},{"name":"Fantasy","url":"/category/fantasy"},{"name":"Romance","url":"/category/romance"}],"chapters":[{"id":"1585924169625_1","date":"2020/04/10","date_crawled":"2020/04/03","name":"Chapter - 0","url":"/infinite-apostles-and-twelve-war-girls/0"},{"id":"1585924169625_2","date":"2020/04/10","date_crawled":"2020/04/03","name":"Chapter - 1","url":"/infinite-apostles-and-twelve-war-girls/1"},{"id":"1585924169625_3","date":"2020/04/10","date_crawled":"2020/04/03","name":"Chapter - 2","url":"/infinite-apostles-and-twelve-war-girls/2"},{"id":"1585924169625_4","date":"2020/04/10","date_crawled":"2020/04/03","name":"Chapter - 3","url":"/infinite-apostles-and-twelve-war-girls/3"},{"id":"1585924169625_5","date":"2020/04/10","date_crawled":"2020/04/03","name":"Chapter - 4","url":"/infinite-apostles-and-twelve-war-girls/4"},{"id":"1585924169625_6","date":"2020/04/10","date_crawled":"2020/04/03","name":"Chapter - 5","url":"/infinite-apostles-and-twelve-war-girls/5"},{"id":"1585924169625_7","date":"2020/04/10","date_crawled":"2020/04/03","name":"Chapter - 6","url":"/infinite-apostles-and-twelve-war-girls/6"},{"id":"1585924169625_8","date":"2020/04/10","date_crawled":"2020/04/03","name":"Chapter - 7","url":"/infinite-apostles-and-twelve-war-girls/7"},{"id":"1585924169625_9","date":"2020/04/10","date_crawled":"2020/04/05","name":"Chapter - 8","url":"/infinite-apostles-and-twelve-war-girls/8"},{"id":"1585924169625_10","date":"2020/04/19","date_crawled":"2020/04/14","name":"Chapter - 9","url":"/infinite-apostles-and-twelve-war-girls/9"},{"id":"1585924169625_11","date":"2020/04/19","date_crawled":"2020/04/17","name":"Chapter - 10","url":"/infinite-apostles-and-twelve-war-girls/10"},{"id":"1585924169625_12","date":"2020/04/19","date_crawled":"2020/04/17","name":"Chapter - 11","url":"/infinite-apostles-and-twelve-war-girls/11"},{"id":"1585924169625_13","date":"2020/04/19","date_crawled":"2020/04/17","name":"Chapter - 12","url":"/infinite-apostles-and-twelve-war-girls/12"},{"id":"1585924169625_14","date":"2020/04/19","date_crawled":"2020/04/17","name":"Chapter - 13","url":"/infinite-apostles-and-twelve-war-girls/13"},{"id":"1585924169625_15","date":"2020/04/19","date_crawled":"2020/04/17","name":"Chapter - 14","url":"/infinite-apostles-and-twelve-war-girls/14"},{"id":"1585924169625_16","date":"2020/04/19","date_crawled":"2020/04/19","name":"Chapter - 15","url":"/infinite-apostles-and-twelve-war-girls/15"},{"id":"1585924169625_17","date":"2020/04/19","date_crawled":"2020/04/19","name":"Chapter - 16","url":"/infinite-apostles-and-twelve-war-girls/16"},{"id":"1585924169625_18","date":"2020/04/26","date_crawled":"2020/04/22","name":"Chapter - 17","url":"/infinite-apostles-and-twelve-war-girls/17"},{"id":"1585924169625_19","date":"2020/05/03","date_crawled":"2020/04/29","name":"Chapter - 18","url":"/infinite-apostles-and-twelve-war-girls/18"},{"id":"1585924169625_20","date":"2020/05/06","date_crawled":"2020/05/08","name":"Chapter - 19","url":"/infinite-apostles-and-twelve-war-girls/19"},{"id":"1585924169625_21","date":"2020/05/06","date_crawled":"2020/05/08","name":"Chapter - 20","url":"/infinite-apostles-and-twelve-war-girls/20"},{"id":"1585924169625_22","date":"2020/05/10","date_crawled":"2020/05/10","name":"Chapter - 25","url":"/infinite-apostles-and-twelve-war-girls/25"},{"id":"1585924169625_23","date":"2020/05/10","date_crawled":"2020/05/10","name":"Chapter - 26","url":"/infinite-apostles-and-twelve-war-girls/26"}],"date_last_crawled":1589120192772},{"id":1584779512738,"name":"Alma","alternative_name":"アルマ","url":"/alma","status":"Ongoing","type":"Japanese","total_views":"0","date_crawled":"2020/03/21","authors":[{"name":"Mito Shinji","url":"/people/mito-shinji"}],"categories":[{"name":"Action","url":"/category/action"},{"name":"Sci-fi","url":"/category/sci-fi"},{"name":"Seinen","url":"/category/seinen"}],"chapters":[{"id":"1584779512738_1","date":"2019/11/10","date_crawled":"2020/03/21","name":"Chapter - 1","url":"/alma/1"},{"id":"1584779512738_2","date":"2020/02/10","date_crawled":"2020/03/21","name":"Chapter - 2","url":"/alma/2"},{"id":"1584779512738_3","date":"2020/02/10","date_crawled":"2020/03/21","name":"Chapter - 3","url":"/alma/3"},{"id":"1584779512738_4","date":"2020/02/10","date_crawled":"2020/03/21","name":"Chapter - 4","url":"/alma/4"},{"id":"1584779512738_5","date":"2020/03/10","date_crawled":"2020/03/21","name":"Chapter - 5","url":"/alma/5"},{"id":"1584779512738_6","date":"2020/03/10","date_crawled":"2020/03/21","name":"Chapter - 6","url":"/alma/6"},{"id":"1584779512738_7","date":"2020/04/19","date_crawled":"2020/04/15","name":"Chapter - 7","url":"/alma/7"},{"id":"1584779512738_8","date":"2020/05/03","date_crawled":"2020/05/01","name":"Chapter - 8","url":"/alma/8"},{"id":"1584779512738_9","date":"2020/05/10","date_crawled":"2020/05/10","name":"Chapter - 9","url":"/alma/9"}],"photo":"/uploads/posters/1572281204.jpg","date_last_crawled":1589120197954}]